rconfig/__init__.py
rconfig/errors.py
rconfig/_internal/__init__.py
rconfig/_internal/format_utils.py
rconfig/_internal/formatting_registry.py
rconfig/_internal/partial.py
rconfig/_internal/path_utils.py
rconfig/_internal/singleton.py
rconfig/_internal/type_inference.py
rconfig/_internal/type_utils.py
rconfig/composition/CompositionCache.py
rconfig/composition/DependencyAnalyzer.py
rconfig/composition/IncrementalComposer.py
rconfig/composition/InstanceResolver.py
rconfig/composition/Merger.py
rconfig/composition/__init__.py
rconfig/composition/composer.py
rconfig/composition/file_path_resolver.py
rconfig/deprecation/__init__.py
rconfig/deprecation/detector.py
rconfig/deprecation/handler.py
rconfig/deprecation/info.py
rconfig/deprecation/matcher.py
rconfig/deprecation/registry.py
rconfig/diff/__init__.py
rconfig/diff/builder.py
rconfig/diff/diff.py
rconfig/diff/models.py
rconfig/diff/formatting/__init__.py
rconfig/diff/formatting/builtin_layouts.py
rconfig/diff/formatting/builtin_presets.py
rconfig/diff/formatting/flat.py
rconfig/diff/formatting/format.py
rconfig/diff/formatting/layout.py
rconfig/diff/formatting/markdown.py
rconfig/diff/formatting/model.py
rconfig/diff/formatting/registry.py
rconfig/diff/formatting/tree.py
rconfig/export/__init__.py
rconfig/export/base.py
rconfig/export/dict_exporter.py
rconfig/export/file_base.py
rconfig/export/json_exporter.py
rconfig/export/multi_file_exporter.py
rconfig/export/registry.py
rconfig/export/single_file_exporter.py
rconfig/export/toml_exporter.py
rconfig/export/yaml_exporter.py
rconfig/help/__init__.py
rconfig/help/argparse_integration.py
rconfig/help/flat_integration.py
rconfig/help/grouped_integration.py
rconfig/help/integration.py
rconfig/help/multirun_help.py
rconfig/hooks/__init__.py
rconfig/hooks/base.py
rconfig/hooks/models.py
rconfig/hooks/registry.py
rconfig/instantiation/Instantiator.py
rconfig/instantiation/LazyProxy.py
rconfig/instantiation/__init__.py
rconfig/interpolation/__init__.py
reausoconfig-0.1.0.dist-info/METADATA
reausoconfig-0.1.0.dist-info/WHEEL
reausoconfig-0.1.0.dist-info/licenses/LICENSE
reausoconfig-0.1.0.dist-info/RECORD
