Metadata-Version: 2.4
Name: ReausoConfig
Version: 0.1.0
Summary: A Python configuration library that turns YAML, JSON, and TOML files into Python objects
Project-URL: Documentation, https://reauso.github.io/ReausoConfig/
Project-URL: Repository, https://github.com/reauso/ReausoConfig
Project-URL: Issues, https://github.com/reauso/ReausoConfig/issues
Author-email: Rene Ebertowski <r.ebertowski@gmx.de>
License-Expression: MIT
License-File: LICENSE
Requires-Python: >=3.11
Requires-Dist: lark<2.0,>=1.1.0
Requires-Dist: ruamel-yaml<0.19,>=0.18.7
Requires-Dist: tomli-w<2.0,>=1.0.0
Provides-Extra: docs
Requires-Dist: mkdocs-material<10.0,>=9.0.0; extra == 'docs'
Provides-Extra: test
Requires-Dist: attrs<25.0,>=24.0.0; extra == 'test'
Requires-Dist: coverage<8.0,>=7.0.0; extra == 'test'
Requires-Dist: parameterized<1.0,>=0.9.0; extra == 'test'
Requires-Dist: pydantic<3.0,>=2.0.0; extra == 'test'
Requires-Dist: pytest<10.0,>=9.0.0; extra == 'test'
